spotify_music_dl/__init__.py
spotify_music_dl/downloader.py
spotify_music_dl/helpers.py
spotify_music_dl-0.0.6.dist-info/LICENCE
spotify_music_dl-0.0.6.dist-info/METADATA
spotify_music_dl-0.0.6.dist-info/WHEEL
spotify_music_dl-0.0.6.dist-info/RECORD
