Metadata-Version: 2.3
Name: spotify-music-dl
Version: 0.0.6
Summary: A simple tool to download Spotify tracks and playlists
License: MIT
Author: anekobtw
Author-email: krolexonder@gmail.com
Requires-Python: >=3.12,<4.0
Classifier: License :: OSI Approved :: MIT License
Classifier: Programming Language :: Python :: 3
Classifier: Programming Language :: Python :: 3.12
Classifier: Programming Language :: Python :: 3.13
Requires-Dist: aiohttp (>=3.11.11,<4.0.0)
Requires-Dist: coloredlogs (>=15.0.1,<16.0.0)
Requires-Dist: mutagen (>=1.47.0,<2.0.0)
Requires-Dist: spotipy (>=2.25.0,<3.0.0)
Requires-Dist: yt-dlp (>=2025.1.12,<2026.0.0)
Requires-Dist: ytmusicapi (>=1.9.1,<2.0.0)
Project-URL: Repository, https://github.com/anekobtw/spotify_music_dl
